README.md
setup.py
pynominatim/__init__.py
pynominatim/pynominatim.py
pynominatim.egg-info/PKG-INFO
pynominatim.egg-info/SOURCES.txt
pynominatim.egg-info/dependency_links.txt
pynominatim.egg-info/top_level.txt