Metadata-Version: 1.1
Name: pynominatim
Version: 0.3.0
Summary: OSM Nominatim API module
Home-page: https://github.com/Xevib/pynominatim.git
Author: Xavier Barnada
Author-email: xbarnada@gmail.com
License: UNKNOWN
Platform: any
Classifier: Programming Language :: Python :: 2.7
Classifier: Programming Language :: Python :: 3.5
Classifier: License :: OSI Approved :: Apache Software License
Classifier: Natural Language :: English
Classifier: Topic :: Software Development :: Libraries :: Python Modules
